ADsim.py
LICENSE.txt
README.md
setup.py
ADsim.egg-info/PKG-INFO
ADsim.egg-info/SOURCES.txt
ADsim.egg-info/dependency_links.txt
ADsim.egg-info/requires.txt
ADsim.egg-info/top_level.txt