Metadata-Version: 2.1
Name: ADsim
Version: 0.5
Summary: ADsim-module
Home-page: https://www.adwin.de/us/produkte/adsim.html
Author: Markus Borchers
Author-email: info@ADwin.de
Maintainer: Jaeger Computergesteuerte Messtechnik GmbH
License: Apache License, Version 2
Platform: linux2
Platform: win32
License-File: LICENSE.txt
